<?xml version="1.0" encoding="UTF-8"?>
<repomd xmlns="http://linux.duke.edu/metadata/repo">
  <data type="other_db">
    <location href="repodata/other.sqlite.bz2"/>
    <checksum type="sha">e4b66c3012e7089ac7e9f78c1575281da8571c40</checksum>
    <timestamp>1373064077</timestamp>
    <open-checksum type="sha">48c4b9bf1467181eb24fbefd14234c0f7dfeae6f</open-checksum>
    <database_version>10</database_version>
  </data>
  <data type="other">
    <location href="repodata/other.xml.gz"/>
    <checksum type="sha">55cd36a5284cec0c1c196c658063a23c910cbd52</checksum>
    <timestamp>1373064076</timestamp>
    <open-checksum type="sha">25dd9a47662cd30e6d4af3f614da496c722f435b</open-checksum>
  </data>
  <data type="filelists_db">
    <location href="repodata/filelists.sqlite.bz2"/>
    <checksum type="sha">f1a79d3e99be62127c0c792030b89f66b3147541</checksum>
    <timestamp>1373064078</timestamp>
    <open-checksum type="sha">bc75b7fee6ece0d53c7c905c0b3f76818a4d4f16</open-checksum>
    <database_version>10</database_version>
  </data>
  <data type="filelists">
    <location href="repodata/filelists.xml.gz"/>
    <checksum type="sha">3c47b93e0be9f40ee142a1e73a985e121266a14b</checksum>
    <timestamp>1373064076</timestamp>
    <open-checksum type="sha">a096af47af3d74059127cc15992b832172f37b81</open-checksum>
  </data>
  <data type="primary_db">
    <location href="repodata/primary.sqlite.bz2"/>
    <checksum type="sha">e62b26e3cf12cee9501d8634289f288023f1af1f</checksum>
    <timestamp>1373064080</timestamp>
    <open-checksum type="sha">5d75d7cda6c2c3c9cbb940d25d552038f05a409d</open-checksum>
    <database_version>10</database_version>
  </data>
  <data type="primary">
    <location href="repodata/primary.xml.gz"/>
    <checksum type="sha">e78e2498ebb044f405eb577abaea15cda38ba7b6</checksum>
    <timestamp>1373064076</timestamp>
    <open-checksum type="sha">18554140dfbc33f5241ca124ccfd4aaa234add6f</open-checksum>
  </data>
</repomd>
