<?xml version="1.0" encoding="UTF-8"?>
<repomd xmlns="http://linux.duke.edu/metadata/repo">
  <data type="other">
    <location href="repodata/other.xml.gz"/>
    <checksum type="sha">65f71b422412ae1ba69b85cd5db61151d2df28e3</checksum>
    <timestamp>1423053978</timestamp>
    <open-checksum type="sha">4341c9146831ebd5f36cb92559563ff449efed8d</open-checksum>
  </data>
  <data type="filelists">
    <location href="repodata/filelists.xml.gz"/>
    <checksum type="sha">45fe6c3ed214b45667c952e28a48c297af1470c4</checksum>
    <timestamp>1423053978</timestamp>
    <open-checksum type="sha">7d0726f1712896689f24d5747659657f72e657d7</open-checksum>
  </data>
  <data type="primary">
    <location href="repodata/primary.xml.gz"/>
    <checksum type="sha">f0249ded8782a3b28253b8d616309ac429ea0d02</checksum>
    <timestamp>1423053978</timestamp>
    <open-checksum type="sha">4524a9aa6c281912d67989e5ec85c16fafecf036</open-checksum>
  </data>
</repomd>
