<?xml version="1.0" encoding="UTF-8"?>
<repomd xmlns="http://linux.duke.edu/metadata/repo">
  <data type="other">
    <location href="repodata/other.xml.gz"/>
    <checksum type="sha">9b5d136b4573a79b61468d06d22dcc21c11159d8</checksum>
    <timestamp>1412009420</timestamp>
    <open-checksum type="sha">61e8f9ec384037b0ac8f73a16a50335e390e1ed8</open-checksum>
  </data>
  <data type="filelists">
    <location href="repodata/filelists.xml.gz"/>
    <checksum type="sha">9d98e56f8f684d7f4fbcf06ebaaefc36de923f96</checksum>
    <timestamp>1412009420</timestamp>
    <open-checksum type="sha">99913c6169df9d60c1d03dd821f220ff7848fbee</open-checksum>
  </data>
  <data type="primary">
    <location href="repodata/primary.xml.gz"/>
    <checksum type="sha">abc6178aabeeec823f8fafaf92b10b24eb8f5155</checksum>
    <timestamp>1412009420</timestamp>
    <open-checksum type="sha">7ed1608e65485a529421cea6ec94bd3ecb8f27af</open-checksum>
  </data>
</repomd>
