<?xml version="1.0" encoding="UTF-8"?>
<repomd xmlns="http://linux.duke.edu/metadata/repo">
  <data type="other">
    <location href="repodata/other.xml.gz"/>
    <checksum type="sha">6bd8d89b7977bfa6123a8a7fd7cf6c92486562b2</checksum>
    <timestamp>1394034851</timestamp>
    <open-checksum type="sha">1d51911904fb1fc114e73d274b2ec46ec64e2be8</open-checksum>
  </data>
  <data type="filelists">
    <location href="repodata/filelists.xml.gz"/>
    <checksum type="sha">f816c8042001d9202b7048ba80ab7fdbdcc0c84f</checksum>
    <timestamp>1394034851</timestamp>
    <open-checksum type="sha">b82eb3f2f86e2cfeb5196b9f896294ec3acec98d</open-checksum>
  </data>
  <data type="primary">
    <location href="repodata/primary.xml.gz"/>
    <checksum type="sha">cf717e5b6e3d1237367a0977a1f535a9cf6d913c</checksum>
    <timestamp>1394034851</timestamp>
    <open-checksum type="sha">8eaeaa14f3273e2e6c2448687f635188f65d9378</open-checksum>
  </data>
</repomd>
