<?xml version="1.0" encoding="UTF-8"?>
<repomd xmlns="http://linux.duke.edu/metadata/repo">
  <data type="other">
    <location href="repodata/other.xml.gz"/>
    <checksum type="sha">b1b3f0b878865fcd38df316a8178cb560437aff9</checksum>
    <timestamp>1423533094</timestamp>
    <open-checksum type="sha">4557d26efa266996795baa62e031fc83b2451c6f</open-checksum>
  </data>
  <data type="filelists">
    <location href="repodata/filelists.xml.gz"/>
    <checksum type="sha">092a5ff69aae1e7542a9dc03d532bcb9b32e217b</checksum>
    <timestamp>1423533094</timestamp>
    <open-checksum type="sha">19275d9d7458f9b27bd6872137c2ba5e99f20994</open-checksum>
  </data>
  <data type="primary">
    <location href="repodata/primary.xml.gz"/>
    <checksum type="sha">5d8bee441c5ae6b9965280324f29ef4e9fc52769</checksum>
    <timestamp>1423533094</timestamp>
    <open-checksum type="sha">9e79cd9b217c5704ce43191d99ea26e8c7032546</open-checksum>
  </data>
</repomd>
