<?xml version="1.0" encoding="UTF-8"?>
<repomd xmlns="http://linux.duke.edu/metadata/repo">
  <data type="other">
    <location href="repodata/other.xml.gz"/>
    <checksum type="sha">842b333487d1237a116e1f7ad9ca75195c762959</checksum>
    <timestamp>1445532719</timestamp>
    <open-checksum type="sha">95582a6362b048037da1a0552eaa23b32297184a</open-checksum>
  </data>
  <data type="filelists">
    <location href="repodata/filelists.xml.gz"/>
    <checksum type="sha">82b48fe01ad5de60d33ea076ef66798fa5f6e92f</checksum>
    <timestamp>1445532719</timestamp>
    <open-checksum type="sha">918e00f89b5136f8e58ed7691c6d506d3f2c5bf8</open-checksum>
  </data>
  <data type="primary">
    <location href="repodata/primary.xml.gz"/>
    <checksum type="sha">8c8b56d4f9af2fb923d01ef53525e5333a83fcb5</checksum>
    <timestamp>1445532719</timestamp>
    <open-checksum type="sha">ad1cc0df603faa7b5e402610b32dd3fb4f87fc1e</open-checksum>
  </data>
</repomd>
