<?xml version="1.0" encoding="UTF-8"?>
<repomd xmlns="http://linux.duke.edu/metadata/repo">
  <data type="other">
    <location href="repodata/other.xml.gz"/>
    <checksum type="sha">3dd98a0817d7af791123c8b812d5452471899bf8</checksum>
    <timestamp>1423975402</timestamp>
    <open-checksum type="sha">8a25800435a3ed2ae1179817d44d2c97519f7097</open-checksum>
  </data>
  <data type="filelists">
    <location href="repodata/filelists.xml.gz"/>
    <checksum type="sha">3894dae44841968be6574db7d8c336e7d3b4675f</checksum>
    <timestamp>1423975402</timestamp>
    <open-checksum type="sha">af8ca889e872902a79a955bc20a1ebcb0a594ff9</open-checksum>
  </data>
  <data type="primary">
    <location href="repodata/primary.xml.gz"/>
    <checksum type="sha">e463a6fee148222426316a33f8b6fa9fceb973f5</checksum>
    <timestamp>1423975402</timestamp>
    <open-checksum type="sha">7fc521b49cee18eb05b80c4f6e201ce42864d33c</open-checksum>
  </data>
</repomd>
