<?xml version="1.0" encoding="UTF-8"?>
<repomd xmlns="http://linux.duke.edu/metadata/repo">
  <data type="other">
    <location href="repodata/other.xml.gz"/>
    <checksum type="sha">a0ea356ce9d07c2d0ea9473449fc948a8510d501</checksum>
    <timestamp>1398088883</timestamp>
    <open-checksum type="sha">b31719a2150b155c881581da78afa95050e05a4c</open-checksum>
  </data>
  <data type="filelists">
    <location href="repodata/filelists.xml.gz"/>
    <checksum type="sha">e42fba18e43320e8428f32343b0505813e11e662</checksum>
    <timestamp>1398088883</timestamp>
    <open-checksum type="sha">4e10a8d99a0181aa4c04246c4f83d27731522af3</open-checksum>
  </data>
  <data type="primary">
    <location href="repodata/primary.xml.gz"/>
    <checksum type="sha">fedf52c38e70ebc7cd999c517f529c47b4599317</checksum>
    <timestamp>1398088883</timestamp>
    <open-checksum type="sha">b851b77781be92905e95243219760d023f055874</open-checksum>
  </data>
</repomd>
