<?xml version="1.0" encoding="UTF-8"?>
<repomd xmlns="http://linux.duke.edu/metadata/repo">
  <data type="other">
    <location href="repodata/other.xml.gz"/>
    <checksum type="sha">bfa23bd1e70b0de2f65a75efd51e4cede71dde8e</checksum>
    <timestamp>1412432677</timestamp>
    <open-checksum type="sha">0de905c68dd2938bfed26bb756ff95c6da32a9c1</open-checksum>
  </data>
  <data type="filelists">
    <location href="repodata/filelists.xml.gz"/>
    <checksum type="sha">9cab3a29bfad8528b74fd8e0d5b3612b8d5319fa</checksum>
    <timestamp>1412432677</timestamp>
    <open-checksum type="sha">b60bb5091c9c1ac7ec126074c1723501e22d3c05</open-checksum>
  </data>
  <data type="primary">
    <location href="repodata/primary.xml.gz"/>
    <checksum type="sha">759ff3a588fdbdcea6f8e93ec0ddfd65a7ee62f9</checksum>
    <timestamp>1412432677</timestamp>
    <open-checksum type="sha">0730fc77e5c762660b7bb8339a046483aad92141</open-checksum>
  </data>
</repomd>
