<?xml version="1.0" encoding="UTF-8"?>
<repomd xmlns="http://linux.duke.edu/metadata/repo">
  <data type="other">
    <location href="repodata/other.xml.gz"/>
    <checksum type="sha">6b7020a8be010b9bc19bf1f36f564a2450a1254c</checksum>
    <timestamp>1380562232</timestamp>
    <open-checksum type="sha">f47e1f68166b68db5bf53a2c2e5862b40f4faaba</open-checksum>
  </data>
  <data type="filelists">
    <location href="repodata/filelists.xml.gz"/>
    <checksum type="sha">4371027a5e3e89bec5dd9e5e87cf80f4a19a5b77</checksum>
    <timestamp>1380562232</timestamp>
    <open-checksum type="sha">293711b3ec5c1555ffcf057b9422e982170a8d10</open-checksum>
  </data>
  <data type="primary">
    <location href="repodata/primary.xml.gz"/>
    <checksum type="sha">f548764b5d489d3c955e34bc62e50b97fee25696</checksum>
    <timestamp>1380562232</timestamp>
    <open-checksum type="sha">2f4d207d1cdc91afcc5106353903ba1ba5b98547</open-checksum>
  </data>
</repomd>
