<?xml version="1.0" encoding="UTF-8"?>
<repomd xmlns="http://linux.duke.edu/metadata/repo">
  <data type="other">
    <location href="repodata/other.xml.gz"/>
    <checksum type="sha">a93dbb4e4733729534f8850ae4f97fcfc6ad50e0</checksum>
    <timestamp>1452510892</timestamp>
    <open-checksum type="sha">4441da45e4d359ac9d524582f80aa35f80cb59cf</open-checksum>
  </data>
  <data type="filelists">
    <location href="repodata/filelists.xml.gz"/>
    <checksum type="sha">544578e8415990b84262b19c4e45316441c2a0e3</checksum>
    <timestamp>1452510892</timestamp>
    <open-checksum type="sha">19260803eb46caef3103cee410906325d63117ad</open-checksum>
  </data>
  <data type="primary">
    <location href="repodata/primary.xml.gz"/>
    <checksum type="sha">39e4d3c06b95b826f704375ec637d707812e3643</checksum>
    <timestamp>1452510892</timestamp>
    <open-checksum type="sha">49307b61b904b61afeab40ff3a20dbc93e7c1359</open-checksum>
  </data>
</repomd>
