<?xml version="1.0" encoding="UTF-8"?>
<repomd xmlns="http://linux.duke.edu/metadata/repo">
  <data type="other">
    <location href="repodata/other.xml.gz"/>
    <checksum type="sha">db688386f705865a6a58e480b2b919b918f87ca2</checksum>
    <timestamp>1426100346</timestamp>
    <open-checksum type="sha">3901013d5bc2f31d76f501f80bfbae8c4b34689d</open-checksum>
  </data>
  <data type="filelists">
    <location href="repodata/filelists.xml.gz"/>
    <checksum type="sha">6a48c30c631d7795cf54de6e2e51bf4b5b09fdad</checksum>
    <timestamp>1426100346</timestamp>
    <open-checksum type="sha">5cae444fab85c6b57f612b4233b58b39f7bf60f5</open-checksum>
  </data>
  <data type="primary">
    <location href="repodata/primary.xml.gz"/>
    <checksum type="sha">759abb6ab86d84d842c80ed491372f45c56836c9</checksum>
    <timestamp>1426100346</timestamp>
    <open-checksum type="sha">c60b053493de6afe1b2c0ca346a02fe15c76b5de</open-checksum>
  </data>
</repomd>
