<?xml version="1.0" encoding="UTF-8"?>
<repomd xmlns="http://linux.duke.edu/metadata/repo">
  <data type="other">
    <location href="repodata/other.xml.gz"/>
    <checksum type="sha">e274136ecf2712949a68774b4e0a763499f59964</checksum>
    <timestamp>1421161407</timestamp>
    <open-checksum type="sha">35506dbf3741bd39e8af766f9e34b4838b319dc3</open-checksum>
  </data>
  <data type="filelists">
    <location href="repodata/filelists.xml.gz"/>
    <checksum type="sha">450d05ea9ded5f45430a35be4b63924f0ef00b8a</checksum>
    <timestamp>1421161407</timestamp>
    <open-checksum type="sha">59c1aff94de1904d7757099c9aedece53d650e2f</open-checksum>
  </data>
  <data type="primary">
    <location href="repodata/primary.xml.gz"/>
    <checksum type="sha">a181552e716403b484e61830a63636e7e8a0611d</checksum>
    <timestamp>1421161407</timestamp>
    <open-checksum type="sha">c6c5bafbe82d9e9a3b3cac564f026f7a2c1333eb</open-checksum>
  </data>
</repomd>
