<?xml version="1.0" encoding="UTF-8"?>
<repomd xmlns="http://linux.duke.edu/metadata/repo">
  <data type="other">
    <location href="repodata/other.xml.gz"/>
    <checksum type="sha">ecb133455b611bca7bdf1f3e56a8909fefe3b9d8</checksum>
    <timestamp>1388741376</timestamp>
    <open-checksum type="sha">2adc0b32314e1bc4e2bec82e7c8634ac94cc9cc7</open-checksum>
  </data>
  <data type="filelists">
    <location href="repodata/filelists.xml.gz"/>
    <checksum type="sha">06787680052bffa33a262e51f255b0a339bfa320</checksum>
    <timestamp>1388741376</timestamp>
    <open-checksum type="sha">826b30555ba34f3b89dc51bd28b4455abec38a2d</open-checksum>
  </data>
  <data type="primary">
    <location href="repodata/primary.xml.gz"/>
    <checksum type="sha">71bf0ec768ca36be1ca16c883b11b1b993ec0c7c</checksum>
    <timestamp>1388741376</timestamp>
    <open-checksum type="sha">d29bd7d0bd9de92e3615a81d4f3b0dbcf4e346a1</open-checksum>
  </data>
</repomd>
