<?xml version="1.0" encoding="UTF-8"?>
<repomd xmlns="http://linux.duke.edu/metadata/repo">
  <data type="other">
    <location href="repodata/other.xml.gz"/>
    <checksum type="sha">4a53ea219b5a7dc908afec16ccd36aa567449f26</checksum>
    <timestamp>1413521680</timestamp>
    <open-checksum type="sha">b81e330920e5946a79c2cd81e7d7bf7a24a62209</open-checksum>
  </data>
  <data type="filelists">
    <location href="repodata/filelists.xml.gz"/>
    <checksum type="sha">5ba0ce9817bc522ece940ecc893591b711adc8b6</checksum>
    <timestamp>1413521680</timestamp>
    <open-checksum type="sha">bd63d0d70c07276a295424e5cf78ede98574351a</open-checksum>
  </data>
  <data type="primary">
    <location href="repodata/primary.xml.gz"/>
    <checksum type="sha">f7ed7d5ed0fa7709e4498a2a28040c6bb9ee730e</checksum>
    <timestamp>1413521680</timestamp>
    <open-checksum type="sha">b14aa57bcacf91459dfe4439746233d84e743870</open-checksum>
  </data>
</repomd>
