<?xml version="1.0" encoding="UTF-8"?>
<repomd xmlns="http://linux.duke.edu/metadata/repo">
  <data type="other_db">
    <location href="repodata/other.sqlite.bz2"/>
    <checksum type="sha">325230f0d5ae624b13f6d0c90d809f0b0e057e74</checksum>
    <timestamp>1364212664</timestamp>
    <open-checksum type="sha">5ed952df903dccedad0e1db976fe33f4ad9c895e</open-checksum>
    <database_version>10</database_version>
  </data>
  <data type="other">
    <location href="repodata/other.xml.gz"/>
    <checksum type="sha">daf936844a6224bfbda3856ad4b07174d504d71d</checksum>
    <timestamp>1364212664</timestamp>
    <open-checksum type="sha">3edc51e499a19e3f9068d5b3f44bccc5b1a3c84c</open-checksum>
  </data>
  <data type="filelists_db">
    <location href="repodata/filelists.sqlite.bz2"/>
    <checksum type="sha">29ef5c9f0f2d86965d285ab494695d6a3c8515e4</checksum>
    <timestamp>1364212665</timestamp>
    <open-checksum type="sha">f09c591a97e19b6fcb0b016ac13df06304787973</open-checksum>
    <database_version>10</database_version>
  </data>
  <data type="filelists">
    <location href="repodata/filelists.xml.gz"/>
    <checksum type="sha">77e81afd3d37bf779151523ca2edab83a0c9f894</checksum>
    <timestamp>1364212664</timestamp>
    <open-checksum type="sha">4b3a22ce065078fb492e6cc11d995e44a6423f9c</open-checksum>
  </data>
  <data type="primary_db">
    <location href="repodata/primary.sqlite.bz2"/>
    <checksum type="sha">81e1482a2c61987d0ef27951f17963ac36bdf39d</checksum>
    <timestamp>1364212667</timestamp>
    <open-checksum type="sha">5da082f6700f8213e8c4b33b9e06272da92c16e0</open-checksum>
    <database_version>10</database_version>
  </data>
  <data type="primary">
    <location href="repodata/primary.xml.gz"/>
    <checksum type="sha">9791cc7961c0c61b0fdb08a5ad2c9f1a2e20c788</checksum>
    <timestamp>1364212664</timestamp>
    <open-checksum type="sha">a3b13cccd8f4172256a2bc21c444ee3f162b37af</open-checksum>
  </data>
</repomd>
