<?xml version="1.0" encoding="UTF-8"?>
<repomd xmlns="http://linux.duke.edu/metadata/repo">
  <data type="other">
    <location href="repodata/other.xml.gz"/>
    <checksum type="sha">1d2441847a67ca2f43556edfe013e10d5aeda6db</checksum>
    <timestamp>1398577271</timestamp>
    <open-checksum type="sha">f5ac57405def25c301954e301075abff4f6054bd</open-checksum>
  </data>
  <data type="filelists">
    <location href="repodata/filelists.xml.gz"/>
    <checksum type="sha">ff0eb3c817183439e2fe20671eea048aa3337adf</checksum>
    <timestamp>1398577271</timestamp>
    <open-checksum type="sha">19c45f0620132e022dd1f52b2e40e3276a2cebd2</open-checksum>
  </data>
  <data type="primary">
    <location href="repodata/primary.xml.gz"/>
    <checksum type="sha">7eb3ca1b48abea00b2c56d664984f6e2a6ee89a1</checksum>
    <timestamp>1398577271</timestamp>
    <open-checksum type="sha">053810af2cd3ba06fd0e944c3a681b0b60fd68f9</open-checksum>
  </data>
</repomd>
