<?xml version="1.0" encoding="UTF-8"?>
<repomd xmlns="http://linux.duke.edu/metadata/repo">
  <data type="other">
    <location href="repodata/other.xml.gz"/>
    <checksum type="sha">a31b5dd8fce93c26f050eb6b3d523910505aaf74</checksum>
    <timestamp>1391149736</timestamp>
    <open-checksum type="sha">a92056aac58541542431a54721b09abaee48c31e</open-checksum>
  </data>
  <data type="filelists">
    <location href="repodata/filelists.xml.gz"/>
    <checksum type="sha">9300e8fae969be4a272254761de8d78e046280fc</checksum>
    <timestamp>1391149736</timestamp>
    <open-checksum type="sha">9b52c20d881bbb50548abcd961cd61eede757af9</open-checksum>
  </data>
  <data type="primary">
    <location href="repodata/primary.xml.gz"/>
    <checksum type="sha">2943f0a6f414236c7de5a11cc5eb407918f19f49</checksum>
    <timestamp>1391149736</timestamp>
    <open-checksum type="sha">a72ea8ccac0d5a02d92f87ff2c14b32cbe6b23b9</open-checksum>
  </data>
</repomd>
