<?xml version="1.0" encoding="UTF-8"?>
<repomd xmlns="http://linux.duke.edu/metadata/repo">
  <data type="other_db">
    <location href="repodata/other.sqlite.bz2"/>
    <checksum type="sha">f2a03b70aacb830b56da34eecbeb5ed54264c579</checksum>
    <timestamp>1367002486</timestamp>
    <open-checksum type="sha">488e30ce830be96ac8fa1f5646899aac1afcf978</open-checksum>
    <database_version>10</database_version>
  </data>
  <data type="other">
    <location href="repodata/other.xml.gz"/>
    <checksum type="sha">8d26d8f7f73c98c0a4e2cab0c3abb208f79f4adf</checksum>
    <timestamp>1367002485</timestamp>
    <open-checksum type="sha">8e19b0f0257512df2870aeaa927827d7eb5605d2</open-checksum>
  </data>
  <data type="filelists_db">
    <location href="repodata/filelists.sqlite.bz2"/>
    <checksum type="sha">5740483dcc1bf359279c3aab0cf3307f6bad3153</checksum>
    <timestamp>1367002487</timestamp>
    <open-checksum type="sha">76a043a9711dbd3b6272a9a309da37dd1e6b9665</open-checksum>
    <database_version>10</database_version>
  </data>
  <data type="filelists">
    <location href="repodata/filelists.xml.gz"/>
    <checksum type="sha">77cda6dcfdb5354c74302fdf4ed62e5a9ee168de</checksum>
    <timestamp>1367002485</timestamp>
    <open-checksum type="sha">75b52f56f96dea476ecf3a0de2caae5da4d25d35</open-checksum>
  </data>
  <data type="primary_db">
    <location href="repodata/primary.sqlite.bz2"/>
    <checksum type="sha">ee36ab8200b641199d902174ddbc222ca191a290</checksum>
    <timestamp>1367002491</timestamp>
    <open-checksum type="sha">b4be7810f0306bd1a3255b5baece0470b8a7bdb5</open-checksum>
    <database_version>10</database_version>
  </data>
  <data type="primary">
    <location href="repodata/primary.xml.gz"/>
    <checksum type="sha">5479c185e04b7e4117066506768e2f871913653c</checksum>
    <timestamp>1367002485</timestamp>
    <open-checksum type="sha">63b886b848792d77313d1f2949d4a2e7ce91a272</open-checksum>
  </data>
</repomd>
