<?xml version="1.0" encoding="UTF-8"?>
<repomd xmlns="http://linux.duke.edu/metadata/repo">
  <data type="other_db">
    <location href="repodata/other.sqlite.bz2"/>
    <checksum type="sha">f2fbb6c1b1062c14b9ed8d9998cbb34de6273550</checksum>
    <timestamp>1371337769</timestamp>
    <open-checksum type="sha">671a7c77db75bc779b5d599259969d66cb038c59</open-checksum>
    <database_version>10</database_version>
  </data>
  <data type="other">
    <location href="repodata/other.xml.gz"/>
    <checksum type="sha">ad5464fc4ba666b92812dd814ccd6faea47b4382</checksum>
    <timestamp>1371337768</timestamp>
    <open-checksum type="sha">170fce60533d9709969e653c26797434dcc1e7dc</open-checksum>
  </data>
  <data type="filelists_db">
    <location href="repodata/filelists.sqlite.bz2"/>
    <checksum type="sha">2d2412150ebdfaa5a58349276288fe336279d7b3</checksum>
    <timestamp>1371337770</timestamp>
    <open-checksum type="sha">0e08b7fafe1327d6b45bb096a9120025e5ebeed7</open-checksum>
    <database_version>10</database_version>
  </data>
  <data type="filelists">
    <location href="repodata/filelists.xml.gz"/>
    <checksum type="sha">13d8539423cc0eb9b72c28971da876ea32bd6bb6</checksum>
    <timestamp>1371337768</timestamp>
    <open-checksum type="sha">a81cbaad65378fe2805f244eaa484bf481fbed71</open-checksum>
  </data>
  <data type="primary_db">
    <location href="repodata/primary.sqlite.bz2"/>
    <checksum type="sha">fd2b109a079166b853c48d0979749aae5e305fab</checksum>
    <timestamp>1371337772</timestamp>
    <open-checksum type="sha">627fa572f6671dda35b8f77ad23abd64fe23b0f3</open-checksum>
    <database_version>10</database_version>
  </data>
  <data type="primary">
    <location href="repodata/primary.xml.gz"/>
    <checksum type="sha">ef52ed9d922d1473b4c10e0d374979298b8233b2</checksum>
    <timestamp>1371337768</timestamp>
    <open-checksum type="sha">adc3ca35c20b38c69a74247b0b3b206dd5aa98be</open-checksum>
  </data>
</repomd>
