<?xml version="1.0" encoding="UTF-8"?>
<repomd xmlns="http://linux.duke.edu/metadata/repo">
  <data type="other">
    <location href="repodata/other.xml.gz"/>
    <checksum type="sha">92077cea39dedd8a84d79edb1c9d9c31cd9cdbf6</checksum>
    <timestamp>1412255625</timestamp>
    <open-checksum type="sha">d56e0d1ca1a0196a9d3c367d1629f4e76650a8d8</open-checksum>
  </data>
  <data type="filelists">
    <location href="repodata/filelists.xml.gz"/>
    <checksum type="sha">c41bd11dd4bcd114d85ecaeb447f99a594c6dc9e</checksum>
    <timestamp>1412255625</timestamp>
    <open-checksum type="sha">cd7d9e22adbe74b678f3da32a4beb6596b576bf7</open-checksum>
  </data>
  <data type="primary">
    <location href="repodata/primary.xml.gz"/>
    <checksum type="sha">4d54fdbb879ab77b068fcaf3a5530a0ef2a7f5ad</checksum>
    <timestamp>1412255625</timestamp>
    <open-checksum type="sha">926b74040d59f22b8964dbb43b7f23c1ba3f8951</open-checksum>
  </data>
</repomd>
