<?xml version="1.0" encoding="UTF-8"?>
<repomd xmlns="http://linux.duke.edu/metadata/repo">
  <data type="other">
    <location href="repodata/other.xml.gz"/>
    <checksum type="sha">8802f21c7fc53c6457bd7ba4cda701f61861b1db</checksum>
    <timestamp>1378749499</timestamp>
    <open-checksum type="sha">da205719e001fccbdb454ae7a2348cf44f1f184c</open-checksum>
  </data>
  <data type="filelists">
    <location href="repodata/filelists.xml.gz"/>
    <checksum type="sha">88c2a31166be1498c5a30bac149ab99a67f3449a</checksum>
    <timestamp>1378749499</timestamp>
    <open-checksum type="sha">468b0dc41df2df9db0b262085a8cf0119ca82678</open-checksum>
  </data>
  <data type="primary">
    <location href="repodata/primary.xml.gz"/>
    <checksum type="sha">02a029cc1d8dbb55c8a154abd01d50954fb10bfa</checksum>
    <timestamp>1378749499</timestamp>
    <open-checksum type="sha">ad0e8232dad4982748eac5a8129be17c210cd06d</open-checksum>
  </data>
</repomd>
