<?xml version="1.0" encoding="UTF-8"?>
<repomd xmlns="http://linux.duke.edu/metadata/repo">
  <data type="other">
    <location href="repodata/other.xml.gz"/>
    <checksum type="sha">f86989861ea20588eef2013d31ac43a87775c1bc</checksum>
    <timestamp>1398088981</timestamp>
    <open-checksum type="sha">f83dd8f1764654d26f3f2a82c6d4d3fab35269b7</open-checksum>
  </data>
  <data type="filelists">
    <location href="repodata/filelists.xml.gz"/>
    <checksum type="sha">2d3cb07f417462b0cc7f4122bc7371d71b2dfcde</checksum>
    <timestamp>1398088981</timestamp>
    <open-checksum type="sha">24647003c38abdee570157877f2179557c53261e</open-checksum>
  </data>
  <data type="primary">
    <location href="repodata/primary.xml.gz"/>
    <checksum type="sha">ea547ae341f19755915367ef027a153df7ab7ef5</checksum>
    <timestamp>1398088981</timestamp>
    <open-checksum type="sha">776bc6ef93eb94194bf9fa1bda6358e446f5553d</open-checksum>
  </data>
</repomd>
