<?xml version="1.0" encoding="UTF-8"?>
<repomd xmlns="http://linux.duke.edu/metadata/repo">
  <data type="other">
    <location href="repodata/other.xml.gz"/>
    <checksum type="sha">fb92c3d4ef191498e3f6f0164ee5ef7343e2324d</checksum>
    <timestamp>1403187652</timestamp>
    <open-checksum type="sha">4be3c55091f29a2a7ae84b7a0ea43f277c7488c5</open-checksum>
  </data>
  <data type="filelists">
    <location href="repodata/filelists.xml.gz"/>
    <checksum type="sha">78ad5c4627136e929c6397802c4a1d62ab4f17be</checksum>
    <timestamp>1403187652</timestamp>
    <open-checksum type="sha">12fca3d574e2d8ac2a1562d52d2b28f555b11351</open-checksum>
  </data>
  <data type="primary">
    <location href="repodata/primary.xml.gz"/>
    <checksum type="sha">66d2d2e6fbb4410bc5ae2b095f9a8e58dee4a050</checksum>
    <timestamp>1403187652</timestamp>
    <open-checksum type="sha">527f1242901d30b8e1b5e261236b77f8fcfc9eb4</open-checksum>
  </data>
</repomd>
